py_zerobyte/__init__.py
py_zerobyte/auth.py
py_zerobyte/backup_schedules.py
py_zerobyte/client.py
py_zerobyte/exceptions.py
py_zerobyte/notifications.py
py_zerobyte/repositories.py
py_zerobyte/snapshots.py
py_zerobyte/system.py
py_zerobyte/volumes.py
py_zerobyte-1.2.1.dist-info/licenses/LICENSE
tests/__init__.py
tests/test_client.py
py_zerobyte-1.2.1.dist-info/METADATA
py_zerobyte-1.2.1.dist-info/WHEEL
py_zerobyte-1.2.1.dist-info/top_level.txt
py_zerobyte-1.2.1.dist-info/RECORD
