Metadata-Version: 2.4
Name: py-zerobyte
Version: 1.2.1
Summary: Python SDK for Zerobyte API - Manage volumes, backups, and snapshots
Home-page: https://github.com/t0mer/py-zerobyte
Author: Tomer Klein
Author-email: Tomer Klein <tomer.klein@gmail.com>
License: MIT
Project-URL: Homepage, https://github.com/t0mer/py-zerobyte
Project-URL: Repository, https://github.com/t0mer/py-zerobyte
Classifier: Development Status :: 4 - Beta
Classifier: Intended Audience :: Developers
Classifier: Topic :: Software Development :: Libraries :: Python Modules
Classifier: License :: OSI Approved :: MIT License
Classifier: Programming Language :: Python :: 3
Classifier: Programming Language :: Python :: 3.7
Classifier: Programming Language :: Python :: 3.8
Classifier: Programming Language :: Python :: 3.9
Classifier: Programming Language :: Python :: 3.10
Classifier: Programming Language :: Python :: 3.11
Requires-Python: >=3.7
License-File: LICENSE
Requires-Dist: requests>=2.25.0
Provides-Extra: dev
Requires-Dist: pytest>=6.0; extra == "dev"
Requires-Dist: pytest-cov>=2.0; extra == "dev"
Requires-Dist: black>=21.0; extra == "dev"
Requires-Dist: flake8>=3.9; extra == "dev"
Dynamic: author
Dynamic: home-page
Dynamic: license-file
Dynamic: requires-python
